pycv_crossvalidation/CrossValidation.py
pycv_crossvalidation/__init__.py
pycv_crossvalidation-0.0.3.dist-info/LICENSE.txt
pycv_crossvalidation-0.0.3.dist-info/METADATA
pycv_crossvalidation-0.0.3.dist-info/WHEEL
pycv_crossvalidation-0.0.3.dist-info/top_level.txt
pycv_crossvalidation-0.0.3.dist-info/RECORD
