Metadata-Version: 2.1
Name: pycv_crossvalidation
Version: 0.0.3
Summary: Python Package for Cross Validation
Home-page: https://github.com/DiogoApostolo/pycv
Author: Diogo Apostolo
Author-email: ogoid.478@gmail.com
Classifier: Programming Language :: Python :: 3
Classifier: License :: OSI Approved :: MIT License
Classifier: Operating System :: OS Independent
Requires-Python: >=3.7
License-File: LICENSE.txt
